{"authorDailyContributionsMap":{"tricixg":[],"jengoc415":[{"date":"2023-02-24","commitResults":[{"hash":"719e0eb3592b81e2b12911da4628831f355887e3","messageTitle":"Replaced email field with pay rate","messageBody":"","fileTypesAndContributionMap":{"functional-code":{"insertions":133,"deletions":166},"docs":{"insertions":4,"deletions":4},"test-code":{"insertions":176,"deletions":225}}},{"hash":"ea0b5943a3afee2f5e2c6d1f797282115e101c57","messageTitle":"Fixed checkstyle errors","messageBody":"","fileTypesAndContributionMap":{"functional-code":{"insertions":33,"deletions":10},"test-code":{"insertions":43,"deletions":19}}}]},{"date":"2023-02-25","commitResults":[{"hash":"fb9eb65e6639e0bf9a69bd2da68bf33660128f4b","messageTitle":"Bug fixes","messageBody":"","fileTypesAndContributionMap":{"test-code":{"insertions":5,"deletions":5}}}]}],"Tempura-Person":[],"Oliverloo0909":[]},"authorFileTypeContributionMap":{"tricixg":{"docs":0,"functional-code":0,"test-code":0},"jengoc415":{"docs":4,"functional-code":132,"test-code":179},"Tempura-Person":{"docs":0,"functional-code":0,"test-code":0},"Oliverloo0909":{"docs":0,"functional-code":0,"test-code":0}},"authorContributionVariance":{"tricixg":0.0,"jengoc415":65090.02,"Tempura-Person":0.0,"Oliverloo0909":0.0},"authorDisplayNameMap":{"tricixg":"CS2103T-W13-2 GOH ..ICIA","jengoc415":"CS2103T-W13-2 CHIA.. YEE","Tempura-Person":"CS2103T-W13-2 LEON..ZHEN","Oliverloo0909":"CS2103T-W13-2 OLIV..HENG"}}
